LICENSE
MANIFEST.in
README.rst
setup.cfg
setup.py
glocks/__init__.py
glocks/base.py
glocks/exceptions.py
glocks/locks.py
glocks.egg-info/PKG-INFO
glocks.egg-info/SOURCES.txt
glocks.egg-info/dependency_links.txt
glocks.egg-info/requires.txt
glocks.egg-info/top_level.txt