Metadata-Version: 1.1
Name: glocks
Version: 0.0.0
Summary: ``glocks`` is a set of global locks that use redis to register the locked resource. Variants of the simple (non-reentrant) global lock include reentrant, distrubed and reentrant-distributed locks.
Home-page: https://github.com/anthonyalmarza/glocks
Author: Anthony Almarza
Author-email: UNKNOWN
License: UNKNOWN
Keywords: glocks,global locks,lock,global,locks,reentrant,distributed,redis,twisted
Platform: UNKNOWN
Classifier: Intended Audience :: Developers
Classifier: Natural Language :: English
Classifier: Operating System :: OS Independent
Classifier: Programming Language :: Python
